livebridge_tickaroo/__init__.py
livebridge_tickaroo/common.py
livebridge_tickaroo/target.py
livebridge_tickaroo/converters/__init__.py
livebridge_tickaroo/converters/liveblog_tickaroo.py
livebridge_tickaroo-0.0.14.dist-info/METADATA
livebridge_tickaroo-0.0.14.dist-info/WHEEL
livebridge_tickaroo-0.0.14.dist-info/top_level.txt
livebridge_tickaroo-0.0.14.dist-info/RECORD
