Metadata-Version: 2.1
Name: livebridge-tickaroo
Version: 0.0.14
Summary: Livebridge adapter for Tickaroo.
Home-page: https://github.com/tickaroo/livebridge-tickaroo
Author: Tickaroo GmbH
Maintainer: Andreas Gerauer
Maintainer-email: andi@tickaroo.com
License: Apache Software License (http://www.apache.org/licenses/LICENSE-2.0)
Keywords: liveticker,tickaroo,syndication
Platform: UNKNOWN
Classifier: Programming Language :: Python :: 3.5
Classifier: Topic :: Communications :: Chat
Classifier: Development Status :: 4 - Beta
Classifier: License :: OSI Approved :: Apache Software License
Classifier: Intended Audience :: Other Audience
Classifier: Operating System :: POSIX :: Linux
Classifier: Environment :: Console
Classifier: Environment :: Plugins
Requires-Dist: livebridge (>=0.10.0)
Requires-Dist: beautifulsoup4
